setup.py
tencentyun/__init__.py
tencentyun/auth.py
tencentyun/conf.py
tencentyun/image.py
tencentyun/imagev2.py
tencentyun/video.py
tencentyun.egg-info/PKG-INFO
tencentyun.egg-info/SOURCES.txt
tencentyun.egg-info/dependency_links.txt
tencentyun.egg-info/requires.txt
tencentyun.egg-info/top_level.txt