Metadata-Version: 1.0
Name: tencentyun
Version: 2.0.0
Summary: python sdk for app.qcloud.com
Home-page: UNKNOWN
Author: jayli
Author-email: jayli@tencent.com
License: MIT License
Keywords: tencentyun,qcloud
Platform: any
